[
  {
    "id": 408477,
    "author": "Peter Wright",
    "authorUrl": "",
    "date": "2018-12-22T05:58:56",
    "content": "<p>I wonder if she had a phantom pregnancy?</p>\n",
    "parent": 0
  },
  {
    "id": 408319,
    "author": "Phil",
    "authorUrl": "",
    "date": "2018-12-13T14:10:35",
    "content": "<p>To Linda,</p>\n<p>Hated that show, never watched it.</p>\n",
    "parent": 0
  },
  {
    "id": 408310,
    "author": "Linda Collison",
    "authorUrl": "http://www.lindacollison.com",
    "date": "2018-12-12T23:09:22",
    "content": "<p>To Phil,<br />\nThe Ghost &amp; Mrs. Muir</p>\n",
    "parent": 0
  },
  {
    "id": 408309,
    "author": "Linda Collison",
    "authorUrl": "http://www.lindacollison.com",
    "date": "2018-12-12T23:04:47",
    "content": "<p>This just raises all sorts of questions</p>\n",
    "parent": 0
  },
  {
    "id": 408306,
    "author": "Phil",
    "authorUrl": "",
    "date": "2018-12-12T17:23:00",
    "content": "<p>She must have watched on regular TV or DVD this movie.</p>\n<p>High Spirits<br />\n1988 ‧<br />\nHorror/Comedy<br />\nhorror ‧ 1h 39m</p>\n<p>When two actual<br />\nghosts, Mary (Daryl<br />\nHannah) and Martin<br />\n(Liam Neeson), show<br />\nup to add some<br />\nauthenticity, they end<br />\nup falling for two<br />\nguests, Sharon (Beverly<br />\nD&#8217;Angelo) and Jack<br />\n(Steve Guttenberg).</p>\n",
    "parent": 0
  },
  {
    "id": 408305,
    "author": "Phil",
    "authorUrl": "",
    "date": "2018-12-12T17:18:14",
    "content": "<p>Watched on Network tv news, just plain stupid B.S.</p>\n",
    "parent": 0
  },
  {
    "id": 408300,
    "author": "Michael McGee",
    "authorUrl": "",
    "date": "2018-12-12T09:51:43",
    "content": "<p>Those May-December, ghost relationships seldom last!</p>\n",
    "parent": 0
  },
  {
    "id": 408299,
    "author": "Jean-Pierre Declemy",
    "authorUrl": "",
    "date": "2018-12-12T08:58:05",
    "content": "<p>When is she publishing her book &#8220;How to get stupid friends to give you wedding presents&#8221;?</p>\n",
    "parent": 0
  }
]