[
  {
    "id": 412124,
    "author": "John Pascoe",
    "authorUrl": "",
    "date": "2019-09-08T12:23:00",
    "content": "<p>Having called at St Helena many times when serving as an Officer with Union Castle during the fourties and fifties, I was always facinated by the Island, the charm of the people and our cricket matches on the most unusual pitch in the world surely. Even landing swinging on a rope was an adventure.<br />\nI am full of admiration for Captain Bennett having reached her position having come from this remote,lovely place. Capt.  J P</p>\n",
    "parent": 0
  },
  {
    "id": 411929,
    "author": "Roger",
    "authorUrl": "",
    "date": "2019-08-24T23:43:28",
    "content": "<p>Congratulations Captain Bennett.</p>\n",
    "parent": 0
  }
]