[
  {
    "id": 413690,
    "author": "Rick Spilman",
    "authorUrl": "http://www.oldsaltblog.com",
    "date": "2020-03-07T10:14:25",
    "content": "<p>Humans emit 100 times more CO2 than volcanoes. At this point, climate change denial is simply ignorant. </p>\n<p><a href=\"https://skepticalscience.com/volcanoes-and-global-warming.htm\" rel=\"nofollow ugc\">https://skepticalscience.com/volcanoes-and-global-warming.htm</a></p>\n",
    "parent": 413689
  },
  {
    "id": 413689,
    "author": "Sailor Pauly",
    "authorUrl": "",
    "date": "2020-03-07T09:01:55",
    "content": "<p>This global warming/human being are ruining the planet nonsense has gone too far&#8230;</p>\n<p>4 days ago a very average volcano in Indonesia violently erupted&#8230;scientists confirm that in 12 hours of spew, it released more CO2 into the atmosphere than the driving of EVERY automobile EVER PRODUCED.</p>\n<p>Clothes fibers in the ocean?  SO WHAT!  Human life expectancy has almost tripled in a mere 500 years BECAUSE of modern inventions, better clothes, modern medicine, things produced in factories.</p>\n",
    "parent": 0
  }
]