[
  {
    "id": 407014,
    "author": "Jean-pierre Declemy",
    "authorUrl": "",
    "date": "2018-09-04T09:22:19",
    "content": "<p>A textured hull in a high sediment estuary would soon see the barnacle resistant texture coated in mud and be rendered useless. A problem we have with all current antifouls. 🙁</p>\n",
    "parent": 0
  },
  {
    "id": 407004,
    "author": "Carolina Salguero",
    "authorUrl": "http://www.portsidenewyork.org%20and%20www.redhookwaterstories.org",
    "date": "2018-09-02T18:11:07",
    "content": "<p>Once upon a time, a marine coatings business in Red Hook, Brooklyn had a huge collection of barnacles, part of their study into how to defeat these critters <a href=\"https://redhookwaterstories.org/items/show/63\" rel=\"nofollow ugc\">https://redhookwaterstories.org/items/show/63</a></p>\n",
    "parent": 0
  }
]