[
  {
    "id": 411859,
    "author": "Willy",
    "authorUrl": "",
    "date": "2019-08-18T10:59:49",
    "content": "<p>Good question Jean-Pierre</p>\n<p>Amazing how history repeats itself.  </p>\n<p>Sailing ships started with sail.  Then steam and other forms of propulsion.  Now, people are starting to realize that sail power is still profitable.  As a way to cut down on the costs of fuel.</p>\n",
    "parent": 0
  },
  {
    "id": 411856,
    "author": "Michael Taylor",
    "authorUrl": "",
    "date": "2019-08-18T08:46:03",
    "content": "<p>It opens the question as to how many cars could fit on Saint-Pierre Miquelon?</p>\n",
    "parent": 0
  },
  {
    "id": 411854,
    "author": "Jean-Pierre Declemy",
    "authorUrl": "http://Hadlow%20Marine%20Services",
    "date": "2019-08-18T05:04:22",
    "content": "<p>Are the ships to be named Nicole and Papa?</p>\n",
    "parent": 0
  }
]