[
  {
    "id": 405772,
    "author": "Phil",
    "authorUrl": "",
    "date": "2018-03-24T15:42:29",
    "content": "<p>Chasing fish or whale suicide?</p>\n<p>Here&#8217;s an odd one:</p>\n<p>A juvenile<br />\nwhale, believed to be a<br />\nshort-finned pilot whale,<br />\nwas found by a woman<br />\nwalking her dog in the<br />\nLower East Chezzetcook<br />\narea on March 16.<br />\nA pilot whale that washed<br />\nashore in eastern Nova<br />\nScotia could be a warm-<br />\nwater-loving species that&#8217;s<br />\nrarely seen this far north,<br />\naccording to The Marine<br />\nAnimal Response Team.</p>\n",
    "parent": 0
  }
]