[
  {
    "id": 414401,
    "author": "Lisa Smith",
    "authorUrl": "",
    "date": "2020-05-03T13:54:45",
    "content": "<p>The photo posted with this article appears to be from White Bay, BVI, not from USVI.  Water quality tests have recently been performed in many beaches on St John.  All locations had good water quality results.  Perhaps interviewing folks who are on one of these boats would be helpful.</p>\n",
    "parent": 0
  },
  {
    "id": 414396,
    "author": "Jean-Pierre Declemy",
    "authorUrl": "http://Hadlow%20Marine%20Services",
    "date": "2020-05-03T05:32:06",
    "content": "<p>I can visualise a maritime game of musical chairs where, as a boat in a prime spot ups anchor to go offshore to pump out all the other boats will be bumping onto each other trying to get their anchor down in the location first.<br />\nI hope they are not destroying the seabed ecosystem in the process. Mooring buoys are a better solution but it needs organisation to pay for the buoys, their maintenance and collecting mooring fees.</p>\n",
    "parent": 0
  }
]