[
  {
    "id": 417306,
    "author": "Willy",
    "authorUrl": "",
    "date": "2020-10-31T09:31:20",
    "content": "<p>Tho I am really surprised no gunner bothered to take out the stack (chimney).  Take out the stack and the draft is gone.  No draft and the boiler cant make steam as well.  Granted the boat was really a floating gun platform.  The steam engine would have only been needed to facilitate the aiming of the guns.</p>\n",
    "parent": 0
  },
  {
    "id": 417303,
    "author": "Willy",
    "authorUrl": "",
    "date": "2020-10-30T21:57:25",
    "content": "<p>Considering a steam ship had not been built yet.  It is certainly different.  Tho I think it was ungainly in the manuevering.  It certainly would be a interesting model to build.</p>\n",
    "parent": 0
  }
]