[
  {
    "id": 412154,
    "author": "D. Peter Boucher, Kt. SMOM, International Master Mariner",
    "authorUrl": "http://formerly%20NAUTICAL%20LOG%20no%20longer%20published",
    "date": "2019-09-12T10:44:07",
    "content": "<p>One found this extremely interesting having spent 50 years at sea.  Quite a bit of that time was spent crossing the Pacific Ocean and trading between numerous Pacific Islands. Also two years were spent living in New Zealand yet never saw or heard of these events occurring.</p>\n<p>Good Watch</p>\n",
    "parent": 0
  }
]