[
  {
    "id": 440387,
    "author": "Jean-Pierre Declemy",
    "authorUrl": "",
    "date": "2024-11-04T06:22:26",
    "content": "<p>Fortunately Peter they seem to be putting her back into service rather than making her a museum ship.</p>\n",
    "parent": 0
  },
  {
    "id": 440363,
    "author": "Peter Wright",
    "authorUrl": "",
    "date": "2024-10-31T14:46:21",
    "content": "<p>An iconic and well deserving vessel of preservation but how do you convince Joe Public?</p>\n<p>Alongside it is unimpressive, in deep water it is inaccessible. </p>\n<p>A real and present conundrum for a vessel that has contributed so much to our understanding of the oceans.</p>\n",
    "parent": 0
  }
]