[
  {
    "id": 411772,
    "author": "Willy",
    "authorUrl": "",
    "date": "2019-08-09T17:06:56",
    "content": "<p>Just a hunch here, yet the lack of refrigeration would be a problem.</p>\n<p>Love the comment Phil.</p>\n<p>The facebook link has a privacy setting that is not set tto public.  Readers should use the craigslist link.</p>\n",
    "parent": 0
  },
  {
    "id": 411771,
    "author": "Phil",
    "authorUrl": "",
    "date": "2019-08-09T15:16:58",
    "content": "<p>My one room flat is bigger!</p>\n",
    "parent": 0
  }
]