[
  {
    "id": 423621,
    "author": "Carolann",
    "authorUrl": "",
    "date": "2021-10-17T11:26:41",
    "content": "<p>My grandfather served on the USS Bear 1939-41 as Admiral Byrd’s radioman in Antarctica, and then off Greenland when we entered the war, patrolling for Nazi ships and submarines.</p>\n",
    "parent": 0
  },
  {
    "id": 423586,
    "author": "Earl",
    "authorUrl": "",
    "date": "2021-10-15T20:03:03",
    "content": "<p>Another bit of nautical history that I hadn’t heard before. I really enjoy the blog. Thanks</p>\n",
    "parent": 0
  }
]